sct/__init__.py
sct/config.py
sct/sct.py
sct/scripts/__init__.py
sct/scripts/download_nltk_stopwords.py
sct/utils/__init__.py
sct/utils/constants.py
sct/utils/contact.py
sct/utils/datetime.py
sct/utils/ner.py
sct/utils/normtext.py
sct/utils/resources.py
sct/utils/special.py
sct/utils/stopwords.py
tests/__init__.py
tests/test_sct.py
SqueakyCleanText-0.3.0.dist-info/LICENSE
SqueakyCleanText-0.3.0.dist-info/METADATA
SqueakyCleanText-0.3.0.dist-info/WHEEL
SqueakyCleanText-0.3.0.dist-info/entry_points.txt
SqueakyCleanText-0.3.0.dist-info/top_level.txt
SqueakyCleanText-0.3.0.dist-info/RECORD
