Metadata-Version: 2.1
Name: SqueakyCleanText
Version: 0.3.0
Summary: A comprehensive text cleaning and preprocessing pipeline.
Home-page: https://github.com/rhnfzl/SqueakyCleanText
Author: Rehan Fazal
License: MIT
Keywords: text cleaning,text preprocessing,NLP,natural language processing
Classifier: Programming Language :: Python :: 3
Classifier: Programming Language :: Python :: 3.10
Classifier: Programming Language :: Python :: 3.11
Classifier: Programming Language :: Python :: 3.12
Classifier: License :: OSI Approved :: MIT License
Classifier: Operating System :: OS Independent
Classifier: Topic :: Software Development :: Libraries
Classifier: Topic :: Text Processing
Requires-Python: >=3.10
License-File: LICENSE
Requires-Dist: lingua-language-detector>=2.0.2
Requires-Dist: nltk>=3.8
Requires-Dist: emoji>=2.8
Requires-Dist: ftfy>=6.1
Requires-Dist: Unidecode>=1.3
Requires-Dist: beautifulsoup4>=4.12
Requires-Dist: transformers>=4.30
Requires-Dist: torch>=2.0.0
Requires-Dist: presidio-anonymizer>=2.2.355
Provides-Extra: dev
Requires-Dist: hypothesis==6.82.7; extra == "dev"
Requires-Dist: faker==20.1.0; extra == "dev"
Requires-Dist: flake8==6.1.0; extra == "dev"
Requires-Dist: pytest==7.5.0; extra == "dev"
Requires-Dist: timeout-decorator==0.5.0; extra == "dev"
Provides-Extra: test
Requires-Dist: coverage==7.3.1; extra == "test"
Requires-Dist: pytest-cov==4.1.0; extra == "test"
